README.md
setup.py
matils/__init__.py
matils.egg-info/PKG-INFO
matils.egg-info/SOURCES.txt
matils.egg-info/dependency_links.txt
matils.egg-info/top_level.txt
matils/patterns/__init__.py
matils/patterns/observer.py
tests/__init__.py
tests/patterns/__init__.py
tests/patterns/test_observer.py