Metadata-Version: 1.2
Name: matils
Version: 0.1.1
Summary: Collection of utilities using only the Python Standard                  Library
Home-page: https://github.com/mathiasbrito/matils
Author: Mathias Santos de Brito
Author-email: mathias.brito@me.com
Maintainer: Mathias Santos de Brito
Maintainer-email: mathias.brito@me.com
License: UNKNOWN
Platform: UNKNOWN
